dpcpp_llvm_spirv/__init__.py
dpcpp_llvm_spirv/_helper.py
dpcpp_llvm_spirv/_version.py
dpcpp_llvm_spirv/bin/llvm-spirv
dpcpp_llvm_spirv/lib/libonnxruntime.1.12.22.721.so
dpcpp_llvm_spirv-2024.2.0.dist-info/METADATA
dpcpp_llvm_spirv-2024.2.0.dist-info/WHEEL
dpcpp_llvm_spirv-2024.2.0.dist-info/top_level.txt
dpcpp_llvm_spirv-2024.2.0.dist-info/RECORD
