Metadata-Version: 2.1
Name: dpcpp-llvm-spirv
Version: 2024.2.0
Summary: llvm-spirv helper
Home-page: https://github.com/IntelPython/dpcpp-llvm-spirv
Author: Intel Corp.
Author-email: scripting@intel.com
License: Intel End User License Agreement for Developer Tools
Classifier: Development Status :: 5 - Production/Stable
Classifier: Programming Language :: Python :: 3.8
Classifier: Programming Language :: Python :: 3.9
Classifier: Programming Language :: Python :: 3.10
